[{"id": "1526303258410729474", "name": "JAMES", "username": "jamesfromcourt"}, {"id": "2280967279", "name": "Ian Runkle/Runkle of the Bailey @ YouTube", "username": "IanRunkle"}, {"id": "2407993940", "name": "Doge", "username": "IntelDoge"}, {"id": "1201283865144369152", "name": "march\u2077\u2718", "username": "goldisjin"}, {"id": "889017472229154817", "name": "eden\u2077", "username": "taehyunglegend"}, {"id": "95092020", "name": "Dr Jordan B Peterson", "username": "jordanbpeterson"}, {"id": "377075561", "name": "The DUI Guy+", "username": "KyDUIGuy"}, {"id": "22594853", "name": "Emily D. Baker \u2696\ufe0f \ud83d\udc9c", "username": "TheEmilyDBaker"}, {"id": "1285190394301616130", "name": "\ud835\udc91.", "username": "IavenderfieIds"}, {"id": "1243131596716355584", "name": "carriebradshaw \ud83d\udd4a", "username": "pradasunset"}, {"id": "1420977475178225664", "name": "EVA", "username": "cloudninethings"}, {"id": "1206901566487375872", "name": "n.", "username": "whatndever"}, {"id": "1330370580642721792", "name": "\ud835\udc87.", "username": "momentsofence"}, {"id": "1404107843570221069", "name": "niamh", "username": "etherealfairies"}, {"id": "1314182158513299457", "name": "Dominique Dupr\u00e9-Henry", "username": "DuprDominique2"}, {"id": "375852740", "name": "Sara Gonzales", "username": "SaraGonzalesTX"}, {"id": "1346462220813697025", "name": "\ud835\ude38\ud835\ude22\ud835\ude2f\ud835\ude25\ud835\ude26\ud835\ude33\ud835\ude2d\ud835\ude36\ud835\ude34\ud835\ude35", "username": "dachosenlibra"}, {"id": "1438558820217851905", "name": "\ud835\udcd9", "username": "pradaamoon"}, {"id": "1103128491988606977", "name": "\ud835\udc04.", "username": "MAISONSTLAURENT"}, {"id": "772680317522051072", "name": "\ud835\udc9c\ud835\udcb9\ud835\udcb6\ud835\udc9e\ud835\udcb6\ud835\udcc9\ud835\udcb6\ud835\udcc1\ud835\udcbe\ud835\udcc3\ud835\udcb6\ud83e\udd0d", "username": "adacatalinaa"}, {"id": "1409178453937594371", "name": "may", "username": "scarlettwants"}, {"id": "1433506249732235266", "name": "sam \u0fd4", "username": "fulminarey"}, {"id": "1328719831500279814", "name": "RappelConso", "username": "RappelConso"}, {"id": "31047836", "name": "Michael Knowles \ud83e\udec3\ud83c\udffb", "username": "michaeljknowles"}, {"id": "1105029164", "name": "Brad Wilcox", "username": "BradWilcoxIFS"}, {"id": "133236438", "name": "Maxime Thi\u00e9baut", "username": "MaximeThiebaut"}, {"id": "1142343182", "name": "Academia Christiana", "username": "AcademiaChristi"}, {"id": "1434553194324152322", "name": "Blemont Denis", "username": "BlemontD"}, {"id": "1453743157963857926", "name": "VERITY France", "username": "verity_france"}, {"id": "170404151", "name": "Juan Branco \u270a", "username": "anatolium"}, {"id": "827151086733635584", "name": "Barbara78", "username": "dragonduclos"}, {"id": "1165570989490659329", "name": "Gauthier Le Bret", "username": "GauthierBret"}, {"id": "18396319", "name": "CNEWS", "username": "CNEWS"}, {"id": "1228708590036320258", "name": "Lo\u00efc Guermeur \ud83c\udf0a\u2693\ufe0f\ud83c\udf0a", "username": "CapHornier_"}, {"id": "94875636", "name": "St\u00e9phane Edouard", "username": "HommesInfluence"}, {"id": "310203348", "name": "Matthieu Delormeau", "username": "Mdelormeau"}, {"id": "1494318619", "name": "Vida y \u00c9tica", "username": "bio_etica"}, {"id": "1444975301495250945", "name": "D\u00e9codage Zemmour", "username": "DecodageZemmour"}, {"id": "973684455725350915", "name": "Parler", "username": "parler_app"}, {"id": "1388116611626852358", "name": "G\u00e9n\u00e9ration Z | Pays de la Loire", "username": "GenerationZPL"}, {"id": "572861750", "name": "Maud Koffler", "username": "MaudPK"}, {"id": "1332701906892939264", "name": "Cocarde Nantes", "username": "NantesCocarde"}, {"id": "1038091753411293185", "name": "Stanislas Rigault", "username": "stanislasrig"}, {"id": "3272501735", "name": "Matthieu Louves \u0646", "username": "LouvesMatthieu"}, {"id": "3707794701", "name": "Jean Louis", "username": "JL7508"}, {"id": "378632690", "name": "Cyril Hanouna", "username": "Cyrilhanouna"}, {"id": "832766641", "name": "TPMP", "username": "TPMP"}, {"id": "1357358878674059265", "name": "Livre Noir", "username": "Livrenoirmedia"}, {"id": "1386675245982027776", "name": "Les Femmes Avec Zemmour", "username": "FemmesZemmour"}, {"id": "1346890637690499074", "name": "Alexandra Henrion-Caude", "username": "CaudeHenrion"}, {"id": "2798085759", "name": "Naonedbus Live", "username": "naonedbuslive"}, {"id": "902835412120383488", "name": "asole grey \ud83e\udda2\ud83c\udf38", "username": "asolegrey"}, {"id": "1319730040494542849", "name": "G\u00e9n\u00e9ration Zemmour \u24e9", "username": "GenerationZ_off"}, {"id": "472412809", "name": "Florian Philippot", "username": "f_philippot"}, {"id": "865950601242443776", "name": "kaley :)", "username": "jesuslovecoffee"}, {"id": "1250512712620281857", "name": "Association Victimes Covid-19 France \ud83c\uddeb\ud83c\uddf7", "username": "AssoCovid"}, {"id": "76004287", "name": "Big Brother Watch", "username": "BigBrotherWatch"}, {"id": "472852289", "name": "Br\u00e8ves de presse", "username": "Brevesdepresse"}, {"id": "1256267262446764032", "name": "Historygirl", "username": "janeyellene"}, {"id": "1183418538285027329", "name": "Eric Zemmour", "username": "ZemmourEric"}, {"id": "398785825", "name": "Fabrice Di Vizio", "username": "DIVIZIO1"}, {"id": "1244280931357208585", "name": "Laissonslesprescrire", "username": "Laissonslespre1"}, {"id": "1344502928212561920", "name": "\ub2c8\ud0a4 (qdeoks)", "username": "rubberdeokies"}, {"id": "1296476006828527617", "name": "Crypto 0M\ud83d\udcc8", "username": "om_crypto"}, {"id": "726868178920415232", "name": "Cryptofactsofficial \ud83c\udf0d", "username": "CryptofactsON"}, {"id": "231792522", "name": "Evias", "username": "teratogenese"}, {"id": "1257557583335796736", "name": "Cardano Updates", "username": "cardano_updates"}, {"id": "1376161898", "name": "Charles Hoskinson", "username": "IOHK_Charles"}, {"id": "1371106690481934337", "name": "COMMUNAUT\u00c9 FRANCOPHONE DU SHIB (CFDS)", "username": "Shiba_fr"}, {"id": "933026518854504449", "name": "Whaleagent Crypto \ud83d\udc51\u20bf", "username": "WhaleAgents"}, {"id": "1388513315165548545", "name": "Romain - Crypto Lab\ud83e\uddea\ud83e\uddea", "username": "CryptokenLabo"}, {"id": "1353645944437399553", "name": "Coinonaut", "username": "Coinonaut"}, {"id": "926161115154808832", "name": "Tammi Menendez", "username": "TammiMenendez1"}, {"id": "1303947838854848514", "name": "Filip Poutintsev", "username": "filippoutintsev"}, {"id": "1265925748587556864", "name": "MOONSHOTS\u2122 |NFT PROMOTER\ud83d\udc51", "username": "Cryptonftcalls"}, {"id": "1272166368088113157", "name": "Mila \u2728", "username": "milafique"}, {"id": "2444047345", "name": "Christopher Yger", "username": "MRJINJGLE80"}, {"id": "97672707", "name": "STAR en direct", "username": "STARendirect"}, {"id": "73383656", "name": "Ivan Rioufol \u0646", "username": "ivanrioufol"}, {"id": "1210243580758880257", "name": "\ub0a0\uc544\uc62c\ub77c\u2077", "username": "Ve0613"}, {"id": "878247600096509952", "name": "Candace Owens", "username": "RealCandaceO"}, {"id": "52544275", "name": "Ivanka Trump", "username": "IvankaTrump"}, {"id": "818876014390603776", "name": "Melania Trump 45 Archived", "username": "FLOTUS45"}, {"id": "1283877243173965824", "name": "Honki Vinci (III) #EnSanteEtNonInjecte", "username": "NoliVinci"}, {"id": "259001548", "name": "Kayleigh McEnany", "username": "kayleighmcenany"}, {"id": "138882249", "name": "Black Hole", "username": "konstructivizm"}, {"id": "1308743389412831238", "name": "Sign Languages", "username": "Theuniquepixs"}, {"id": "1138458175663988738", "name": "Pop Base", "username": "PopBase"}, {"id": "493391629", "name": "Waleed Al-husseini", "username": "W_Alhusseini"}, {"id": "16148677", "name": "YAF", "username": "yaf"}, {"id": "1139507664201900034", "name": "QG le m\u00e9dia libre", "username": "LibreQg"}, {"id": "1185918427732553730", "name": "\ube14\ub799\uc561\uc2a4", "username": "blackxagustdMP4"}, {"id": "297508918", "name": "Georges Malbrunot", "username": "Malbrunot"}, {"id": "1190558475396489216", "name": "Fiona Seclit \ud83d\udc89\ud83c\uddee\ud83c\udde8\ud83d\udc89\ud83c\uddee\ud83c\udde8\ud83d\udc89\ud83c\uddee\ud83c\udde8\ud83d\udc89", "username": "FSeclit"}, {"id": "128698096", "name": "Geoffroy Lejeune", "username": "GeoffroyLejeune"}, {"id": "51095169", "name": "Ouest-France 35", "username": "ouestfrance35"}, {"id": "19091173", "name": "Steven Crowder", "username": "scrowder"}, {"id": "2420267570", "name": "Alex Kokcharov", "username": "AlexKokcharov"}, {"id": "270839361", "name": "Matteo Salvini", "username": "matteosalvinimi"}, {"id": "744260935527735296", "name": "chart data", "username": "chartdata"}, {"id": "788677398472560641", "name": "Emma Hollen \ud83d\udd4a\ufe0f\ud83c\uddfa\ud83c\udde6", "username": "Emma_Hollen"}, {"id": "983674932696633344", "name": "\u2606 with you by jimin", "username": "itbabyjimin"}, {"id": "3771624442", "name": "Acad\u00e9mie militaire de Saint-Cyr Co\u00ebtquidan", "username": "SaintCyrCoet"}, {"id": "354301451", "name": "Peace Love Books", "username": "PeaceLuvBooks"}, {"id": "44196397", "name": "Elon Musk", "username": "elonmusk"}, {"id": "2982938111", "name": "\ud83c\udf43\u200f\u064b", "username": "tmbIrpics"}, {"id": "928444328", "name": "ThinkerView", "username": "Thinker_View"}, {"id": "1073948805978943488", "name": "\ud83e\udd5b", "username": "613x218"}, {"id": "941544401662181376", "name": "stella \ud83d\udd4a", "username": "etherealdior"}, {"id": "2783948822", "name": "Ray\u2077", "username": "OT7wrecked"}, {"id": "2367499642", "name": "newt", "username": "milktpapi"}, {"id": "18236230", "name": "Jeffree Star", "username": "JeffreeStar"}, {"id": "1212816126834397184", "name": "Mediavenir Good News", "username": "MediavenirGN"}, {"id": "2394684085", "name": "FichesIDE", "username": "FichesIDE"}, {"id": "92849144", "name": "Fdesouche.com est une revue de presse", "username": "F_Desouche"}, {"id": "83484751", "name": "Serge Federbusch", "username": "sergefederbusch"}, {"id": "25029495", "name": "Pulte", "username": "pulte"}, {"id": "919964888", "name": "LaManifPourTous35", "username": "lmpt35"}, {"id": "762649146", "name": ".", "username": "ARCHIVEDVIEWS"}, {"id": "19879313", "name": "Aubrey Plaza", "username": "evilhag"}, {"id": "189305014", "name": "BNO News", "username": "BNONews"}, {"id": "852787295316918276", "name": "Restitutor Orientis", "username": "RestitutorOrien"}, {"id": "1214315619031478272", "name": "Mediavenir", "username": "Mediavenir"}, {"id": "2499386443", "name": "Justin Bernardez", "username": "JBernardez_"}, {"id": "1176264093902278657", "name": "Les \u00c9tudiants contre la PMA", "username": "EtudContreLaPMA"}, {"id": "26553170", "name": "Abb\u00e9 Grosjean \u0646", "username": "abbegrosjean"}, {"id": "4061586491", "name": "Infos Fran\u00e7aises", "username": "InfosFrancaises"}, {"id": "1681324362", "name": "The Unexplained", "username": "Unexplained"}, {"id": "845973570668810241", "name": "\ud835\uddd5\ud835\ude02\ud835\uddf9\ud835\uddf9\ud835\uddf2\ud835\ude01\ud835\uddfd\ud835\uddff\ud835\uddfc\ud835\uddfc\ud835\uddf3(\ub77c\uc774)\ud83e\udd8b", "username": "bullet_proofly"}, {"id": "102722347", "name": "Jean Lassalle", "username": "jeanlassalle"}, {"id": "806783159794745345", "name": "R\u00e9seau Fr CRPV", "username": "Reseau_CRPV"}, {"id": "1072300501", "name": "Christine KELLY", "username": "christine_kelly"}, {"id": "440914834", "name": "Julien ODOUL", "username": "JulienOdoul"}, {"id": "875696023", "name": "La Manif Pour Tous", "username": "LaManifPourTous"}, {"id": "480454550", "name": "Dioc\u00e8se de Rennes", "username": "DioceseRennes"}, {"id": "3239132428", "name": "La Cocarde \u00c9tudiante", "username": "CocardeEtud"}, {"id": "1074113128173109249", "name": "Lo\u0646is \ud83c\uddeb\ud83c\uddf7", "username": "Louisfanfanfan"}, {"id": "784347608", "name": "Erik Tegn\u00e9r", "username": "tegnererik"}, {"id": "4005052529", "name": "Jimmy Bourlieux \u24c2\ufe0f", "username": "BourlieuxJimmy"}, {"id": "1381367533", "name": "Hdebonnevolonte", "username": "Enfantdabord2"}, {"id": "190015239", "name": "Maxime Alexandre", "username": "presumelibre"}, {"id": "88467525", "name": "Virginie Tellenne \u0646", "username": "FrigideBarjot"}, {"id": "1466616120", "name": "L'Avenir Pour Tous", "username": "AvenirPourTous"}, {"id": "87259899", "name": "Louis de Raguenel", "username": "LouisDeRaguenel"}, {"id": "832799928510476288", "name": "comidas t\u00e3o lindas que parecem voc\u00ea", "username": "food_porn17"}, {"id": "961643720302002177", "name": "French Lives Matter", "username": "FrenchLivesM"}, {"id": "1126749496082223104", "name": "HYBE MERCH", "username": "HYBE_MERCH"}, {"id": "842559446303870976", "name": "Je suis Camille", "username": "CamilleVernier1"}, {"id": "1055219811935027201", "name": "\ud83d\udc69\ud83c\udffc\u200d\ud83d\udcbb", "username": "ethiquebrand"}, {"id": "500713106", "name": "Pape Fran\u00e7ois", "username": "Pontifex_fr"}, {"id": "875821752663900160", "name": "L'ivresse de la peau", "username": "moi_peau"}, {"id": "3092175352", "name": "Alain Delon Fan Page", "username": "DelonFanPage"}, {"id": "1879512708", "name": "BRIGITTE BARDOT", "username": "brigitte_bardot"}, {"id": "246160407", "name": "S\u00e9zane", "username": "SEZANE_PARIS"}, {"id": "2783548694", "name": "STOB IT \u2077 \ud83e\uddc8 \ud83d\udc1f", "username": "amd_ml9"}, {"id": "255305729", "name": "Kristen Callihan", "username": "Kris10Callihan"}, {"id": "1106225370255290368", "name": "TTP", "username": "thetaeprint"}, {"id": "1420564512", "name": "cococcinelle\u25e1\u0308 |\u25bd\u2077", "username": "wasahobii"}, {"id": "1109011576659427328", "name": "Weverse Shop", "username": "weverseshop"}, {"id": "988692701791993856", "name": "Weverse", "username": "weverseofficial"}, {"id": "957447403170422784", "name": "minchu", "username": "minsugacheonye"}, {"id": "1121836045186658304", "name": "\ubdd4\uc624\ub2c8\uc18c\uc2a4 Vionysos\ud83c\udf3f", "username": "Vionysos95"}, {"id": "88462044", "name": "Samuel Lafont", "username": "Samuel_Lafont"}, {"id": "1108491994572177408", "name": "martta \ud83d\udc99\ud83d\udc9b", "username": "gonerosies"}, {"id": "1499400284", "name": "Jordan Bardella", "username": "J_Bardella"}, {"id": "3267440372", "name": "Camila Cabello News", "username": "CCabelloNews"}, {"id": "112754792", "name": "Valeurs actuelles \u0646", "username": "Valeurs"}, {"id": "1491160081", "name": "Niki and Sammy", "username": "nikinsammy"}, {"id": "1129044352548917249", "name": "bts\u2077", "username": "btsgalleria"}, {"id": "904917596847394816", "name": "lucy\u2077\u2022\u2022\u2022", "username": "CEOlambskewer"}, {"id": "1084593187275059200", "name": "wakeupH \ud83d\udc9c AOTY", "username": "wakeup_h"}, {"id": "785096003498156033", "name": "la femme dans l\u2019art", "username": "femmeduart"}, {"id": "228605295", "name": "Tati Westbrook", "username": "GlamLifeGuru"}, {"id": "40364952", "name": "andi \u2077 | \ud83e\udee0\u2763", "username": "Andirang"}, {"id": "2455740283", "name": "MrBeast", "username": "MrBeast"}, {"id": "252751061", "name": "Bloomberg Quicktake", "username": "Quicktake"}, {"id": "1012074332959358976", "name": "\uc218\ucd08\uc774\u2077 \ud83d\udc9c", "username": "SooChoiFolder"}, {"id": "1064287629561085952", "name": "\ud83d\udc25\ud83d\udcce", "username": "gunijimini_see"}, {"id": "735343927696478208", "name": "\ub124\uc2dc\u2077", "username": "Inspiredby_W"}, {"id": "1362342188", "name": "h.", "username": "lilbadksw"}, {"id": "1122028976153812992", "name": "BTSWATCHDOGS \ud83d\udc9c\u2077", "username": "BTSWatchdog_twt"}, {"id": "702175912377380864", "name": "bts pics", "username": "btsxpics"}, {"id": "950283147580755968", "name": "\u1d2e\u1d31VELVET KIM TAEHYUNG\u2077", "username": "taehyungster"}, {"id": "140131880", "name": "Audacy", "username": "Audacy"}, {"id": "978184280", "name": "Damien Rieu", "username": "DamienRieu"}, {"id": "897041328", "name": "Obs Christianophobie", "username": "Christianophobi"}, {"id": "815127831894032384", "name": "\u30a8\u30eb\u2077 \u2665", "username": "BTSxEru"}, {"id": "1033415170565922817", "name": "\ubc15\uc0d0\ub9ac", "username": "misterJJack"}, {"id": "872255844158668806", "name": "Butterfly\u2077", "username": "ButterflyEllaJ"}, {"id": "15825051", "name": "Rafranz", "username": "RafranzDavis"}, {"id": "25365536", "name": "Kim Kardashian", "username": "KimKardashian"}, {"id": "217749896", "name": "Marine Le Pen", "username": "MLP_officiel"}, {"id": "1883836454", "name": "\u2d62\u2d30\u2d59\u2d4e\u2d49\u2d4f\u2d3b", "username": "jasmynetwt"}, {"id": "4020532937", "name": "Tasty", "username": "tasty"}, {"id": "2907408203", "name": "Philippe Murer \ud83c\uddeb\ud83c\uddf7", "username": "PhilippeMurer"}, {"id": "27014121", "name": "Georgetown Cupcake", "username": "GTownCupcake"}, {"id": "850476538688679938", "name": "Reni waiting for cyno\ud83c\udfab\ud83c\udf38 yours \ud83c\udf38", "username": "renixkeaya"}, {"id": "893411582952132608", "name": "naddie \u2077 | bts proof june 10 \ud83d\udc25\ud83d\udc3b", "username": "thebtspop"}, {"id": "321221304", "name": "\uc58c\ubaac\uc774\ud83c\udf37", "username": "yamma_monimoni"}, {"id": "1058344182610300930", "name": "bora \ud83d\udc9c", "username": "modooborahae"}, {"id": "1006198505470349312", "name": "Yassin J. Adam\u2077", "username": "YJAarchive"}, {"id": "924705819018579968", "name": "ITALIAN SKAM", "username": "italianskam"}, {"id": "2342724906", "name": "RYUSERALOVER", "username": "ryuseralover"}, {"id": "1085522008471818240", "name": "mes #TeamPinky", "username": "OH_mes2"}, {"id": "918503722728136705", "name": "\uc624\ub77d-\ub2d8", "username": "im_jammed"}, {"id": "834465214213025792", "name": "\uacf5\uc81c\ubc1c", "username": "Netizentown"}, {"id": "895318918625210368", "name": "s w", "username": "swsecretworld"}, {"id": "1083067529940123651", "name": "TXT Charts\u26a1", "username": "TXTCHART_KR"}, {"id": "1095590659308675075", "name": "ARMYPEDIA", "username": "ARMYPEDIA"}, {"id": "29290083", "name": "Denny Directo", "username": "DDirecto"}, {"id": "938097549143142400", "name": "\ud835\udda9\ud835\udda8\ud835\uddad\ud835\uddc7\ud835\uddc2\ud835\uddbf\ud835\uddbe\ud835\uddcb \u2077", "username": "yoonminmaze"}, {"id": "890958722402582528", "name": "Charles Leclerc Fan Page", "username": "LeclercNews"}, {"id": "262230432", "name": "Charles Leclerc", "username": "Charles_Leclerc"}, {"id": "1088995449724260352", "name": "\ub2ec\ucf64\ud55c\uafc8", "username": "btsweverse13"}, {"id": "1059327333532749824", "name": "TOMORROW X TOGETHER", "username": "TXT_members"}, {"id": "1077909567248482304", "name": "\uc778\ubbf8\ud83d\udc30\ud83c\udfa4", "username": "JK__in_me"}, {"id": "977407537271025665", "name": "\u1d2e\u1d31sai\u2077\ud83c\udf52||JIMIN DAY\ud83d\udc23", "username": "ggeuknim"}, {"id": "909160406639431680", "name": "andrea \u2661s bts\u2077 (\ud83d\udc9b)", "username": "blackxagustd"}, {"id": "1017470813623050241", "name": "BTS dumpling \uff08REST\uff09", "username": "bts_dumpling"}, {"id": "761965039532335104", "name": "\u263c", "username": "JungkookBuzz"}, {"id": "982589192088596481", "name": "HO\ub5a1\ud83c\udf82", "username": "gukphoria____jk"}, {"id": "1083198663424237569", "name": "TXT OFFICIAL", "username": "TXT_bighit"}, {"id": "1081109284513968128", "name": "SMERALDO BOOKS", "username": "Smeraldo_Books"}, {"id": "1907306828", "name": "Ria\u2077 \u25fe\ud83c\udf4e || \u1d3e\u02b3\u1d52\u1d52\u1da0 ||", "username": "__gaciria"}, {"id": "511402689", "name": "World and Science", "username": "WorldAndScience"}, {"id": "34743251", "name": "SpaceX", "username": "SpaceX"}, {"id": "17995040", "name": "Ben Shapiro", "username": "benshapiro"}, {"id": "3226282347", "name": "Insider", "username": "thisisinsider"}, {"id": "955416869552373761", "name": "\ud83e\udd70", "username": "sekfurfwhew1282"}, {"id": "712611353287073792", "name": "pannatic", "username": "pannatic"}, {"id": "3863262613", "name": ".", "username": "kpop_archives"}, {"id": "2924946528", "name": "\uc77c\uac04\uc2a4\ud3ec\uce20 \ud835\udc70\ud835\udc8d\ud835\udc88\ud835\udc82\ud835\udc8f \ud835\udc7a\ud835\udc91\ud835\udc90\ud835\udc93\ud835\udc95\ud835\udc94", "username": "ilgansports"}, {"id": "906222847823138816", "name": "\u21ddalex\u2077\u21dc", "username": "outro_tear_"}, {"id": "1001029225476972545", "name": "Minist\u00e8re de l'Int\u00e9rieur - Alerte", "username": "Beauvau_Alerte"}, {"id": "1943549695", "name": "xiaowoxi\u2077", "username": "xiaowoxi"}, {"id": "728578451561570304", "name": "ChinaJinBar", "username": "ChinaJinBar"}, {"id": "715602537529917440", "name": "\ud835\ude2c\ud835\ude30\ud835\ude33\ud835\ude2f\ud835\ude26\ud835\ude2d\ud835\ude2a\ud835\ude22\u2077", "username": "nellifluos"}, {"id": "1003016102400659457", "name": "\u2730liv##!\u2077", "username": "oommonee"}, {"id": "2413530088", "name": "Becca", "username": "BTSHINee_5"}, {"id": "1033882897554526208", "name": "\ud83d\udc25\ud83d\udcfa", "username": "spjm_vid"}, {"id": "821030451892473856", "name": "\uc9c0\ubbfc salt peach cream", "username": "MelonChim"}, {"id": "4499810243", "name": "breu\ud83c\udf3f", "username": "manjivrou_"}, {"id": "1027541459103174657", "name": "\uc791\uac00 close", "username": "K_M_5813"}, {"id": "981950540325076993", "name": "PeachShake\ud83c\udf51", "username": "PeachShake_jk"}, {"id": "880067243689758720", "name": "moved to @eboyjoonie", "username": "twinktaejin"}, {"id": "1038511077640687617", "name": "RULER.", "username": "RULER_V"}, {"id": "732926369743568896", "name": "\uaf43\ubc94", "username": "RM_PSTGA"}, {"id": "785036116814462976", "name": "\uc778\uc5d4", "username": "IEofgroup"}, {"id": "845889279066746881", "name": "PARKJIMINBAR\ud83d\udc51", "username": "JIMINBAR_CHINA"}, {"id": "2577336475", "name": "\ud83e\udef6\ud83c\udffc", "username": "jikookrelated"}, {"id": "1056812367747543040", "name": "Cherry Bullet (\uccb4\ub9ac\ube14\ub81b)", "username": "cherrybullet"}, {"id": "2347170860", "name": "Miyayeah", "username": "miyaohyeah"}, {"id": "930229570820890626", "name": "After Ever Happy Movie", "username": "aftermovie"}, {"id": "4345817544", "name": "UniVerse PH | BTS V", "username": "UNIVERSE1230"}, {"id": "46484995", "name": "September \u2077 \u26f1\ufe0f", "username": "__WildRose___"}, {"id": "982168619000905730", "name": "taekook\u2077", "username": "kookvtwins"}, {"id": "1020010963800678400", "name": "c", "username": "slutjjk"}, {"id": "1015049238965882881", "name": "S\u2728", "username": "kookblueside"}, {"id": "762142750275801092", "name": "yoonmin love bot \u2661", "username": "sujimworld"}, {"id": "1004380535618064384", "name": "I Dare U", "username": "IDAREU_JK"}, {"id": "1060068723103457280", "name": "BT21club", "username": "bt21club"}, {"id": "916974408379650048", "name": "pre-debut scaramouche stan", "username": "petitdancers"}, {"id": "939754725980889088", "name": "Be\ub098\ub9ac\ud83d\udc9c \u2119\ud835\udd63\ud835\udd60\ud835\udd60\ud835\udd57", "username": "bts_megu613"}, {"id": "934223901403394048", "name": "\ud788\ub098\ucf54", "username": "jimin_v95z"}, {"id": "962708775164661760", "name": "van", "username": "247isheaven"}, {"id": "946228316767424512", "name": "Ahlem\u2077 PR\u27ec\u27ed\u27ec\u27edF", "username": "hopefulmyg"}, {"id": "818571742713155585", "name": "wiktoria\u2077", "username": "yoongispuppy"}, {"id": "854296824982650880", "name": "ONE REASON \uc6d0\ub9ac\uc98c", "username": "ONE_REASON_JK"}, {"id": "4212139273", "name": "\ubc29\uae00\uc655\ubc84\uac70\ud83c\udf54", "username": "BTburger7"}, {"id": "199969903", "name": "\ub808\uc774\ub098\u2763\ufe0f", "username": "cookiemini486"}, {"id": "904285508779483138", "name": "BB", "username": "BTS_BB_"}, {"id": "740931623328186368", "name": "Baddies", "username": "BaddieGods"}, {"id": "16221522", "name": "Simon Falk", "username": "simmnfierzig"}, {"id": "1034338599712374784", "name": "2018MGA_official", "username": "2018MGA"}, {"id": "1053958754784301056", "name": "BTS PRODUCTS | ROSE \ud83e\udd1f\ud83c\udffb\u2728", "username": "btsproducks"}, {"id": "772400913428287488", "name": "\uad6c\ub300\ud83d\udda4", "username": "9_DDaE"}, {"id": "1055034097351835649", "name": "MELTING ON !", "username": "meltingon_"}, {"id": "3020939257", "name": "CLOSED.", "username": "seokjinsremedy"}, {"id": "983270451584487424", "name": "\u200eKV", "username": "kookvlovebot"}, {"id": "998416418818281472", "name": "michelle\u2077", "username": "uwunamjoon"}, {"id": "3845245752", "name": "\u2022\u1d17\u2022\u2727", "username": "aka_mombo"}, {"id": "3253626948", "name": "\ucc21\uc774\ub294 \uc0ac\ube60\ub538\ud83c\udf53", "username": "LoveDearly_BTS"}, {"id": "951467070335598592", "name": "Flying Angel\ud83d\udc25", "username": "FlyingAngel_JM"}, {"id": "991159018633625600", "name": "\ud398\uc774\ub4dc\uc778", "username": "fadein97"}, {"id": "714136147396395008", "name": "cupid.", "username": "Cupid_901"}, {"id": "892058602772381696", "name": "\ub7ec\ube0c\uc2dc\uadf8\ub110", "username": "LUVSIGNAL901"}, {"id": "996637378918928384", "name": "deepdownlow", "username": "deepdownlow97"}, {"id": "947802200935297026", "name": "Be simple", "username": "be_simple97"}, {"id": "736976203198779392", "name": "\ub8e8\ube48", "username": "heaven__JK"}, {"id": "1047162633567125504", "name": "Avatar", "username": "_Avatar__"}, {"id": "477868460", "name": "Shaaay\u2077 \ud83c\udf19 D E E P \ud83d\udd78\ud83d\udd77", "username": "Shay_K_One"}, {"id": "954129038846713857", "name": "\ud83d\udc99", "username": "polarbearyoongi"}, {"id": "546006989", "name": "\u2077", "username": "tfjimin"}, {"id": "897249878136332288", "name": "ale", "username": "jinsathot"}, {"id": "335540047", "name": "NF", "username": "nfrealmusic"}, {"id": "84387190", "name": "Marche Pour La Vie", "username": "MarchePourLaVie"}, {"id": "966077626900246528", "name": "\u300c claire \u2077 \u300d", "username": "btstranslation7"}, {"id": "70427900", "name": "Fondation J\u00e9r\u00f4me Lejeune", "username": "FondLejeune"}, {"id": "2943487978", "name": "\u207f\u1d49\u02e1\u02e1\u02b8\u2077 \ud83d\udc9c", "username": "nelly_jungshook"}, {"id": "1017122798534381568", "name": "\ud83d\udc9c\ud83c\udde8\ud83c\uddf5 Purple Ribbon ARMY \ud83c\udde8\ud83c\uddf5\ud83d\udc9c", "username": "BTS_PRA_FR"}, {"id": "3424559566", "name": "Satisfying Animation", "username": "AnimationVidz"}, {"id": "348292869", "name": "\uad6c\ub2c8\ud83d\udc25", "username": "gunijimini"}, {"id": "975398710808076288", "name": "\ubc29\ud0c4\uc18c\ub144\ub2e8 \u26aa", "username": "BTS_twvt1"}, {"id": "3190492830", "name": "Cindy Kimberly", "username": "wolfiecindy"}, {"id": "729261866531364865", "name": "\u1d2e\u1d31 C misses them\u2077 \ud83c\udfab", "username": "bts_lalalalala"}, {"id": "53901775", "name": "t", "username": "tararaharjo"}, {"id": "869679581753692160", "name": "Emilia \u2661", "username": "gomezdiaries_"}, {"id": "2798633181", "name": "leila", "username": "agustbm7"}, {"id": "923817579881275392", "name": "\ud835\udcec\ud835\udcee\ud835\udcfc\ud835\udcfd\ud835\udcf5\ud835\udcea\ud835\udcff\ud835\udcf2\ud835\udcee_90\ud83d\udc9c", "username": "cestlavie_90"}, {"id": "1014716359303839744", "name": "Big Hit official shop", "username": "BigHitShop"}, {"id": "407617143", "name": "Akroid", "username": "akroidofficial"}, {"id": "978073058165407744", "name": "noha // CLOSED", "username": "pjmmoni"}, {"id": "25226417", "name": "Allegra Shaw", "username": "AllegraShaw"}, {"id": "173676124", "name": "Alexis Ren", "username": "AlexisRen"}, {"id": "3987854225", "name": "\u2605", "username": "houbieee"}, {"id": "3221953368", "name": "\ud835\udc1a\ud835\udc26\ud835\udc1a\ud835\udc32\ud835\udc1a", "username": "blusheseokjin"}, {"id": "989102787387588608", "name": "ARMY\u2077 Protection Squad (SLOW)", "username": "ProtectionArmy"}, {"id": "1956910224", "name": "Kpop on Charts", "username": "SerieTV46"}, {"id": "14159148", "name": "United Nations", "username": "UN"}, {"id": "1002937969630699520", "name": "NIS", "username": "007NIS"}, {"id": "895406254637580293", "name": "Warehouse", "username": "warehousenantes"}, {"id": "971278766524780545", "name": "minnie", "username": "minminnnie1204"}, {"id": "976846539183271936", "name": "BTS\u2019CLOSET", "username": "BtssCloset"}, {"id": "1039159284393635840", "name": "small gochu", "username": "g0chu99"}, {"id": "849902730806050816", "name": "Muse \ud83d\udc51", "username": "MuseOfBTS"}, {"id": "1022239538629029888", "name": "billboard charts", "username": "billboardcharts"}, {"id": "1039334894118219779", "name": "Invictus", "username": "Invictus1013"}, {"id": "38476774", "name": "Trevor Ault", "username": "TrevorLAult"}, {"id": "977408870082428929", "name": "J-ARMY FANBASE (closed)", "username": "JARMYFANBASE"}, {"id": "1576828104", "name": "\ud835\udd4a\ud835\udd52\ud835\udd5e\u00b9\u00b2\u2077 \u0b18(\u0a6d\u02ca\ua4b3\u02cb)\u0a6d\u2727", "username": "cashVoutside"}, {"id": "1011139383154503680", "name": "katie \u2728hoseok \ud83e\udd7a", "username": "jungkookiecat"}, {"id": "794883191802732544", "name": "FULL SUN \ud83d\udc9a\u2600\ufe0f\ud83d\udc9a", "username": "Forever_FullSun"}, {"id": "728922836270645248", "name": "\ucc9c\uc0ac \ud83d\ude07 \uc5d4\uc824", "username": "1004JKookie"}, {"id": "69928625", "name": "Headline Planet", "username": "headlineplanet"}, {"id": "377256924", "name": "Currently Hiatus", "username": "Vsmanito"}, {"id": "2723576594", "name": "WhereRUsitARMYs \ud83c\uddeb\ud83c\uddf7", "username": "WhereRUsitArmy"}, {"id": "816070461071048705", "name": "\ub2e4\ub9b0", "username": "UandME00"}, {"id": "1025292599156850688", "name": "ARMY Associated Press", "username": "ARMY_PRESS"}, {"id": "1010076004000378880", "name": "#\ud574\ube48\u2728", "username": "189512X_K"}, {"id": "9890492", "name": "PETA", "username": "peta"}, {"id": "850537140", "name": "\u7d05\u8449\ud83c\udf41\u2077", "username": "95momiji"}, {"id": "45709328", "name": "h", "username": "halsey"}, {"id": "352715033", "name": "Katie \u2077 \ud83d\udcab\ud83c\udf19", "username": "BTS_tit"}, {"id": "1001635397120679936", "name": "KARMYxIARMY Global Streaming Team", "username": "KARMYxIARMY"}, {"id": "978572585972748289", "name": "(mostly) incorrect sekai", "username": "se_kai94"}, {"id": "1016616415745282048", "name": "soba2018global", "username": "soba2018global"}, {"id": "777546960", "name": "PROD SUGA\u2077 \ud83c\udf4a THAT THAT!", "username": "gayoongi"}, {"id": "971557763536113664", "name": "KOREAN SALES", "username": "koreansales_twt"}, {"id": "14772687", "name": "Shazam", "username": "Shazam"}, {"id": "963491431833890816", "name": "ash\u2077 \u263d\u22c6\uff61\u02da \u22c6", "username": "purple_taekook"}, {"id": "908945273287729152", "name": "Bangtan News Network \ud83d\udc9c\u2077 (HIATUS)", "username": "BangtanNewsNet"}, {"id": "851532243302592512", "name": "zia", "username": "zia_taekook"}, {"id": "1978329234", "name": "\u2077", "username": "ChiIILittleBill"}, {"id": "874265612393922561", "name": "wisha (D-8)", "username": "doyou_bangtan"}, {"id": "747480042", "name": "Kevan Kenney", "username": "KevanKenney"}, {"id": "840434980660555776", "name": "POPPING\u2b50\ufe0fSHOWER", "username": "poppingshower39"}, {"id": "855822981087547393", "name": "Agust\u00edn", "username": "agustin_offc"}, {"id": "795609164", "name": "seokjin \u00f6n\u00fcmden ge\u00e7ti \ud83c\udf4c", "username": "heismyspringday"}, {"id": "284998376", "name": "willow", "username": "ilsansqueen"}, {"id": "1480100041", "name": "\u0645\u0631\u064a\u0645", "username": "lqjikook"}, {"id": "914411145691258880", "name": "sophia", "username": "165sooas"}, {"id": "861869239292096512", "name": "MeltForJK", "username": "meltedchocoIate"}, {"id": "985465562242269184", "name": "\ud83e\udd65JK", "username": "coconuts_jk"}, {"id": "552299475", "name": "emma", "username": "jooningstar"}, {"id": "916600380787757056", "name": "\u2077\u207f\u1d52 \u00b9 \u1d52\u207f \u02b0\u1d52\u1d57 \u00b9\u2070\u2070 \u1d2e\u1d31 \ud83c\udf53", "username": "RMphilosophie"}, {"id": "261886958", "name": "Emma Miller", "username": "emmamilleruk"}, {"id": "1541237000", "name": "Sara\u2728", "username": "sxprs"}, {"id": "1466800782", "name": "\ud83d\udc9c218\ud83d\udc9c", "username": "218_jhope"}, {"id": "1522035318", "name": "\uc288\uac00\ub9e5\uc2dc\uba48", "username": "Suga_Maximum"}, {"id": "955327977025228800", "name": "SAVIOR | \uc138\uc774\ube44\uc5b4", "username": "SAVIOR_SUGA"}, {"id": "3330336214", "name": "PROOF 2022.06.10 | \ud83c\udf3b", "username": "Faradina_92"}, {"id": "948106463330709504", "name": "\u043c\u03b9\u2113\u043atae \u2077", "username": "milktae_jpg"}, {"id": "2855417470", "name": "\u2655BTS\u2655 Support \u2077", "username": "SupportBTS"}, {"id": "895160347291787265", "name": "Crazy \ub204\ub098\ud83d\udc9c", "username": "austina_nee"}, {"id": "841690637141495808", "name": "BPB", "username": "bpbillboard"}, {"id": "793592570521804801", "name": "tas \u2744\ufe0f\ud83c\udf30 | semi-hiatus", "username": "deadleavvs"}, {"id": "872272186463203332", "name": "HP", "username": "hphungkc"}, {"id": "108775893", "name": "Most Requested Live", "username": "MostRequestLive"}, {"id": "850288465", "name": "Gary Trust", "username": "gthot20"}, {"id": "771879288589148160", "name": "\u200e \u2077\u2081\u2083", "username": "Jiminpicss"}, {"id": "921875866832924672", "name": "army unnie", "username": "armyunniesub"}, {"id": "794780851779211264", "name": "(hiatus)BTS Bridge", "username": "BTS_BDG"}, {"id": "964964538834710530", "name": "BTS NYC", "username": "BTSNewYorkCity"}, {"id": "954510770968043520", "name": "\ud83d\udc9c\ud83d\udcdaBTS Book Club\u2077\ud83d\udcda\ud83d\udc9c", "username": "BTSBookClub_twt"}, {"id": "990666103511814144", "name": "\ud83c\udf08", "username": "fakelovestwt"}, {"id": "2388970087", "name": "cherrytkoo", "username": "gcftexts"}, {"id": "3126690418", "name": "\ud835\udcb6\ud835\udccb\ud835\udc52 \u2077 \ud83d\udd4a\u2661", "username": "sakurajimi"}, {"id": "1003461919901040641", "name": "BTS Hashtags\u2077", "username": "BangtanTrends"}, {"id": "789833257575591936", "name": "\ucc10\ub290\ud83d\udc3d", "username": "jjinneu1204"}, {"id": "3257847404", "name": "V", "username": "taetaeonearth"}, {"id": "906654594134106112", "name": "\u263e", "username": "lilyvmin7"}, {"id": "922801282603040768", "name": "J E L", "username": "nochusgaeul"}, {"id": "935864159471779841", "name": "\uc9c4\uc800", "username": "gingerol95"}, {"id": "837576728755089408", "name": "elijah.", "username": "hooncenzo"}, {"id": "1003485227136610304", "name": "LET'S KEEP GOING", "username": "LKG_101295"}, {"id": "2936991853", "name": "SUPER DUPER", "username": "SD_jimin"}, {"id": "835047872299065344", "name": "A White day \ud558\uc580\ub0a0 \ud83c\udf6c", "username": "Awhiteday0309"}, {"id": "926190269304750080", "name": "\uc7c8\uadfc\ucf69\ud83c\udf40", "username": "tinyseokjinnie"}, {"id": "986075731674333189", "name": "BTS CHART DEFENDER", "username": "BTS_KCHARTS"}, {"id": "605006796", "name": "juju\u2077\ud83c\udf5d", "username": "junqbu"}, {"id": "744091683269251072", "name": "\ud835\udc00\ud835\udc0b\ud835\udc0b \ud835\udc07\ud835\udc00\ud835\udc08\ud835\udc0b \ud835\udc13\ud835\udc07\ud835\udc04 \ud835\udc0a\ud835\udc08\ud835\udc0d\ud835\udc06 \ud83d\udc51", "username": "allhailsuga0309"}, {"id": "4733271564", "name": "\uc815\uae30\uc800\uae30\ud83c\udf80\u2077 \u00abCLOSED\u00bb", "username": "u4eakooks_net"}, {"id": "905667138110685184", "name": "\u27ed\u27ec \u2077 \ud83c\udfad", "username": "triviaforseven"}, {"id": "128487133", "name": "MAMA(\uc5e0\ub137\uc544\uc2dc\uc548\ubba4\uc9c1\uc5b4\uc6cc\uc988)", "username": "MnetMAMA"}, {"id": "815800760789106688", "name": "Jayelle_Kdiamond\ud83d\udc8e", "username": "JL_Kdiamond"}, {"id": "984509945843539968", "name": "[rest] cafe \u2077 army", "username": "cafe_army"}, {"id": "928319525585534976", "name": "Afy \u2077", "username": "jintaellect"}, {"id": "988440716564189184", "name": "fan outfits account", "username": "badestoutfit"}, {"id": "877937495706447872", "name": "magic shop", "username": "jikooku"}, {"id": "909831237207965696", "name": "mozzi petal", "username": "MozziPetal_JM"}, {"id": "947874574162522114", "name": "[REST]ReMarkable0912", "username": "ReMarkable0912"}, {"id": "45285318", "name": "hyyh yoonkook forever \ud83d\udc31\u2764\ufe0f\ud83d\udc30", "username": "sleepyoonkooks"}, {"id": "944780139480547328", "name": "\uace8\ub4e0", "username": "Golden_kku"}, {"id": "983922319255941120", "name": "Bangtan Universe \ud83d\udcab [Hiatus]", "username": "BangtanUV"}, {"id": "2999093379", "name": "cindy\ud83d\udc97\u2077", "username": "cinpai"}, {"id": "459154047", "name": "MOVED .", "username": "serendijmn"}, {"id": "712622233999556609", "name": "shi", "username": "gojoism"}, {"id": "824835361062793216", "name": "\ubc29\ud0c4\uc131\uc801\uae30\ub85d (slow)", "username": "BTSrecordbot"}, {"id": "955286239577427968", "name": "Fairyland \ud398\uc5b4\ub9ac\ub79c\ub4dc", "username": "fairyland_JK"}, {"id": "3073197240", "name": "September", "username": "SeptemberJK97"}, {"id": "829557462525059072", "name": "\uafb9\ub098\uc787\ud83e\udd70KOOKNIGHT", "username": "JK_97x91"}, {"id": "2769544544", "name": "\uc9c0\ubbf8", "username": "jiminiesbts"}, {"id": "905053609376677888", "name": "khryss \u2077\u27ec\u27ed #PermissionToDance \ud83e\uddc8| #MONO", "username": "lovemaze912_"}, {"id": "1067786706", "name": "\ud835\ude52\ud835\ude44\ud835\ude4f\ud835\ude43 \ud835\ude54\ud835\ude4a\ud835\ude50, \ud835\ude45\ud835\ude44\ud835\ude48\ud835\ude44\ud835\ude49\ud83d\udc25\ud83d\udc30", "username": "OnlyKM9795"}, {"id": "2966704799", "name": "\u2601\ufe0f\u2601\ufe0f\u2601\ufe0f", "username": "TheEclecticA"}, {"id": "3168272239", "name": "\uc9c0\uafb9\ub370\uc77c\ub9ac", "username": "JIKOOKDAILY"}, {"id": "883806552439828480", "name": "\ud83d\udc25\ud83d\udc2f", "username": "vminloop"}, {"id": "379620203", "name": "Netizen Buzz", "username": "netizenbuzz"}, {"id": "2901046231", "name": "ARMY UNNIE\u2077", "username": "ARMYUNNIESUBS"}, {"id": "826038961739034624", "name": "PROMOTE MY CREW", "username": "getmyhanteo"}, {"id": "939847056713138178", "name": "in common \uc778\ucee4\uba3c", "username": "jin_incommon"}, {"id": "946331657023262720", "name": "Melange", "username": "Melange9597"}, {"id": "894702107881873408", "name": ",", "username": "luminouseven"}, {"id": "846814802072633344", "name": "Gem\u00b9\u00b3 STREAM WITH YOU \ud83d\udc99\ud83d\udc25\ud83c\udf19", "username": "pjmgem"}, {"id": "997880001281146883", "name": "bangstan(2nd)", "username": "bangstan07"}, {"id": "228630523", "name": "iChart\u2122", "username": "instiz_ichart"}, {"id": "3435336672", "name": "LGMobileGlobal", "username": "LGMobileGlobal"}, {"id": "1097193955", "name": "alex\u2077", "username": "gcfsdior"}, {"id": "3308576432", "name": "taehyung pics\u26a1\ufe0f", "username": "taehyungpic"}, {"id": "2242138508", "name": "abcdefghi__lmnopqrstuvwxyz", "username": "ddsjkluv"}, {"id": "969578992339771393", "name": "joy\u2077", "username": "jeonluminous"}, {"id": "207083101", "name": "\ud83d\udc9c", "username": "yowits_maine"}, {"id": "866381533602603008", "name": "\u1d2e\u1d31AGUST D-2\u2077\ud83c\udf19\ud83d\udc9c", "username": "anime4reak"}, {"id": "954466514022948865", "name": "BTS Connection\u2077", "username": "btsconnection"}, {"id": "829121717100371968", "name": "\u029f \u1d07 \u1d07 \u1d22 \u028f \u270c\ufe0f", "username": "leezy_bts"}, {"id": "866054210038661120", "name": "keish isn\u2019t suspended anymore??", "username": "JHSMlCDROP"}, {"id": "824254548428455939", "name": "BTS-CAFAS\ud83c\udde8\ud83c\uddf3", "username": "BTSCAFAS"}, {"id": "2547233548", "name": "Phil Sokowicz", "username": "sokowicz"}, {"id": "151027230", "name": "\ud83c\udf40\u0f3aStacey \u0f3b\u300e - \u300f\ud83c\udf39", "username": "Sunako1582"}, {"id": "301854062", "name": "\ud83c\udf97 DEE ~ JINISE \ud83c\udf97", "username": "LockOutOfHeaven"}, {"id": "81940189", "name": "Keone Madrid", "username": "KeoneMadrid"}, {"id": "781320759054569476", "name": "\uce68\uce68\ubaa8\ub2c8\uc5b8", "username": "chimx2mon"}, {"id": "976328168016633857", "name": "\uff28\uff41\uff59\uff55\uff4e", "username": "Gukki_Vtton"}, {"id": "807793405287763968", "name": "EHEH Area", "username": "TaeTaeArea"}, {"id": "935398444184756224", "name": "\ub538\uae30\ubc99\uae00", "username": "JINzza_love"}, {"id": "896096530461077504", "name": "tira", "username": "taropearlz"}, {"id": "730883334", "name": "r a j a e\u2077 gabi's anti", "username": "jeonsempire"}, {"id": "1385966310", "name": "\u064b", "username": "fixiedusts"}, {"id": "1496541763", "name": "jess\u2077", "username": "siriuslyjess"}, {"id": "4859011673", "name": "\ucc1c\ube14\ub9ac \u2022\u1dc4\u025e\u2022\u1dc5", "username": "jjimvely"}, {"id": "2349527344", "name": "\u2ffb", "username": "dewycheek"}, {"id": "908087808765644801", "name": "HITMAN BANG FANBASE", "username": "HITMAN_FANBASE"}, {"id": "787778195131170817", "name": "JP\ud83e\udeb4\ud83d\ude0a", "username": "agirlinthepark"}, {"id": "987985492988772353", "name": "Twilight\u263d \u22c6\u309c", "username": "twilight__391"}, {"id": "819718546280316928", "name": "cata\u2077 || ia bc work", "username": "vantaeflakes"}, {"id": "917421873025056769", "name": "Aurelia \ud83d\udc9c", "username": "AureliaOT7"}, {"id": "976834933292503041", "name": "LOVE RAIN", "username": "LOVERAIN_V"}, {"id": "2445742608", "name": "EllenDrawings", "username": "ellendrawings"}, {"id": "593140421", "name": "k\u2077", "username": "dearmoon97"}, {"id": "937322901983846400", "name": "SLOW BUT STEADY", "username": "_slowbutsteady"}, {"id": "823211211642826754", "name": "BTS ARMY FRANCE\u2077", "username": "ARMYFRANCE_"}, {"id": "96877126", "name": "Koreaboo", "username": "Koreaboo"}, {"id": "827576275841585152", "name": "Safe0226\ud83d\udc30\u2665\ufe0f", "username": "Sa__PPhirE9497"}, {"id": "977513362551578624", "name": "A.K. | #MyUniverse", "username": "Bangtan_Caramel"}, {"id": "518238007", "name": "Will Njobvu", "username": "will_njo"}, {"id": "887534310923714560", "name": "\ud835\udd1e\ud835\udd2b\ud835\udd1e \u2661", "username": "httpsamey"}, {"id": "746424331220115456", "name": "\u1d3e\u02b3\u1d52\u1d52\u1da0UK BTS ARMY\u2077", "username": "UKBTSARMATION"}, {"id": "925953425539559424", "name": "Smoke in Eyes", "username": "SmokeinEyes_V"}, {"id": "47283664", "name": "\uc544\ube60 \ucd5c\uace0 VITAMIN D", "username": "DrunkenTigerJK"}, {"id": "742344463041757184", "name": "\uc815\uad6d\ud83d\udc9cHEADLINER", "username": "headliner_jk"}, {"id": "981835060197244928", "name": "\ub86f\ub370\uba74\uc138\uc810", "username": "lottedfs_global"}, {"id": "907618896408076288", "name": "\ud83d\udc39\ub2e4\ud574\uba39\uc9c4\ud83d\udc39", "username": "worldwide_jin04"}, {"id": "877444506332741632", "name": "Pick my Prince_JIN\ud83d\udc96", "username": "PickmyPrince_JJ"}, {"id": "939781478287732737", "name": "Jingle Bell% \uc9c4\uae00\ubca8\ud83c\udf90", "username": "JingleBell_1204"}, {"id": "865980343278387201", "name": "jinnie_jelly", "username": "jinnie_jelly"}, {"id": "775756236037828608", "name": "KONI", "username": "btsforever1207"}, {"id": "927570048465563648", "name": "\uc11d\uc9c4\uc7bc\ud83d\udcab", "username": "seokjinjam1204"}, {"id": "866313153138774019", "name": "\uc9c0\ub2c8\ud3ec\uc704\uc2dc genie for wish", "username": "genie921204"}, {"id": "899050502767263744", "name": "AllForMyJIN", "username": "AllForMyJIN"}, {"id": "957266064315842560", "name": "TENDERNESS", "username": "tenderness1204"}, {"id": "826458683810787328", "name": "Jinspiration", "username": "Jinspiration92"}, {"id": "1605833881", "name": "\uc9c4\ud0c0\uc784", "username": "_Jintime"}, {"id": "1672221157", "name": "A LITTLE BRAVER \ud83d\udc2c", "username": "ALittleBraver92"}, {"id": "918781596668280837", "name": "\ub098\uc758 \uc9c4\uc0ac\ub791", "username": "mytruelovetojin"}, {"id": "2797168100", "name": "\uc13c\uc138\uc774\uc158", "username": "sensation1204"}, {"id": "918502670884782080", "name": "\uaca8\uc6b8\uc758 \uae30\uc801\ud83d\udcab Miracle Of Winter", "username": "miraclejin_92"}, {"id": "756223728002953216", "name": "\uff53\uff50\uff4a\uff4d", "username": "sweaterpawschim"}, {"id": "774473276928077824", "name": "VPDLAND \ud83d\udc9c *\u0e40\u0e04\u0e25\u0e35\u0e22\u0e23\u0e4c\u0e02\u0e2d\u0e07\u0e23\u0e2d\u0e2b\u0e19\u0e48\u0e2d\u0e22\u0e19\u0e30\u0e04\u0e30", "username": "vpdland"}, {"id": "881400766187147264", "name": "eternal diamond \ud83d\udc8e", "username": "eternaldiamond_"}, {"id": "792042456707588096", "name": "\uc288\uac00\ub9c8\uc6b4\ud2f4\ud83c\udfd4", "username": "SUGAmountain"}, {"id": "868839864770347009", "name": "MASTERPIECE", "username": "masterpiece_pjm"}, {"id": "735832942585339905", "name": "CLOSE\ud5c8\ub2c8\ubc84\ube14\ud83d\udc1d", "username": "HONEYBUBBLE_"}, {"id": "786712766136455169", "name": "\ub108\ub77c\uc11c \uc88b\uc740 \ub0a0", "username": "goodday_1013"}, {"id": "945688063350423552", "name": "Enchanted \uc9c0\ubbfc \ud83d\udd2e", "username": "EnchantedJM"}, {"id": "787744391523885056", "name": "\ud835\udc03\ud835\udc11\ud835\udc04\ud835\udc00\ud835\udc0c \ud835\udc08\ud835\udc0d \ud835\udc12\ud835\udc0f\ud835\udc11\ud835\udc08\ud835\udc0d\ud835\udc06 \ud83c\udf38", "username": "spring030993"}, {"id": "800049178189512704", "name": "MERRY WHITE\ud83d\udc9b\uba54\ub9ac\ud654\uc774\ud2b8", "username": "MERRYWHITE_JM"}, {"id": "857823498106019841", "name": "Expose Fansites", "username": "expose_fansites"}, {"id": "71585918", "name": "103.7 KISS FM", "username": "KissChattanooga"}, {"id": "21143468", "name": "104.7 KISS FM", "username": "KISSFMPhoenix"}, {"id": "24560836", "name": "Harley Morenstein", "username": "HarleyPlays"}, {"id": "3889536500", "name": "Jungkook Updates", "username": "jeonggukupdates"}, {"id": "961273561020272641", "name": "BTS Serbia\u2077", "username": "BTS__Serbia"}, {"id": "4251447981", "name": "Arm\u00e9e fran\u00e7aise - Op\u00e9rations militaires", "username": "EtatMajorFR"}, {"id": "356042797", "name": "Arm\u00e9e de l'Air et de l'Espace", "username": "Armee_de_lair"}, {"id": "31981324", "name": "Marine nationale", "username": "MarineNationale"}, {"id": "45607154", "name": "Arm\u00e9e de Terre", "username": "armeedeterre"}, {"id": "872347656944857088", "name": "Wandering Shadow", "username": "shadow_twts"}, {"id": "732156491864506370", "name": "POISON \ud83d\udc9c", "username": "PoisonKook0901"}, {"id": "3105826730", "name": "Meech", "username": "DemetriusHarmon"}, {"id": "2184489764", "name": "Gendarmerie nationale", "username": "Gendarmerie"}, {"id": "954887105347452929", "name": "doolset\ud83c\udf4a", "username": "doolsetbangtan"}, {"id": "976110092129980416", "name": "What BTS Actually Said", "username": "whatBTSsaid"}, {"id": "780608466234675200", "name": "First Sight JK stay alive", "username": "firstsight_jk"}, {"id": "786928877188751360", "name": "\ud83c\udff3\ufe0f\u200d\ud83c\udf08 BTS Views\u2077 (BTS Comeback 22.6.10)", "username": "bstwings_views"}, {"id": "879592314510860290", "name": "3 dollah shop \ud83d\uded2", "username": "3dollah_shop"}, {"id": "983512248495648773", "name": "Moved to @cafe_ARMY \u2615\ufe0f\u2665\ufe0f", "username": "613_fancafe"}, {"id": "963622689205141504", "name": "US BTS Shazam & Radio \u2077 | REST |", "username": "STARSonShazam"}, {"id": "942295573557841920", "name": "BTS on Shazam\u2077", "username": "BTSonShazam"}, {"id": "761042704562216967", "name": "K-Pop Charts", "username": "kpopchartsdata"}, {"id": "166138462", "name": "RM: THANK YOU FOR BEING BORN \ud83d\ude0d\ud83d\ude0d\ud83d\ude0d", "username": "jessjinny"}, {"id": "918853006589923330", "name": "J \u2077", "username": "fairyxjjoon"}, {"id": "977036722801225728", "name": "bts pics", "username": "thebtspicts"}, {"id": "476800771", "name": "\ud835\udc54\ud835\udc52\ud835\udcc1 \u2077 | \ud835\udd7b\ud835\udd97\ud835\udd94\ud835\udd94\ud835\udd8b - 06.10.22", "username": "euphoriatay"}, {"id": "2169852941", "name": "VANA\u062a\u2077\u2081\u2081\u2088", "username": "NoPromoKing"}, {"id": "2584094383", "name": "One Stop K-Pop", "username": "onestop_kpop"}, {"id": "982131602514833408", "name": "\u2744WinterSpring\ud83c\udf38", "username": "winterspring923"}, {"id": "4850119178", "name": "\ub18d", "username": "_no_ng_"}, {"id": "211802633", "name": "/d\u0361\u0292\u0252\u0283u\u02d0\u0259/", "username": "juressic"}, {"id": "1304837280", "name": "born singer \ud83e\udd79\u2077\u2741", "username": "miniagustd"}, {"id": "975948326695776257", "name": "Fer \u2077 \u2728", "username": "yoongified93"}, {"id": "847417825849257985", "name": "tannie\u2077 \u2022\u0300\u3145\u2022\u0301 6.10 (slow bc finals)", "username": "taesnowhite"}, {"id": "850795715479482368", "name": "jihope daily", "username": "bestofjihope"}, {"id": "873437345894195201", "name": "hhhg", "username": "qazplmhg"}, {"id": "1482886988", "name": "BTS TUNISIA\u2077\ud280\ub2c8\uc9c0 \ud83c\uddf9\ud83c\uddf3 HIATUS", "username": "BTS_Tunisia"}, {"id": "862351162669842432", "name": "\u2744", "username": "btstar_"}, {"id": "911005548492890112", "name": "CANDY", "username": "hoseokscandy"}, {"id": "442736572", "name": "Patrick van den Hoek", "username": "patrickvdhoek"}, {"id": "2208055752", "name": "ODIE || 6.10.2022 \ud83d\udd0e", "username": "odettemarch"}, {"id": "95788746", "name": "LG\uc804\uc790", "username": "LGElectronics"}, {"id": "802912014951534592", "name": "\uafb9\uc778\ub7ec\ube0c\u2764\ufe0e", "username": "JK_IN_LOVE"}, {"id": "2361981054", "name": "umusicjapan", "username": "umusicjapan"}, {"id": "893821959330381825", "name": "\ub8e8\uc2dc\ud37c", "username": "LuciferVK_"}, {"id": "955283764221014016", "name": "FATE", "username": "fate_jimin"}, {"id": "972592133080219648", "name": "\uba54\ubaa8\ub9ac\uc544", "username": "MEMORIA0613"}, {"id": "2225943444", "name": "RM by RMsthurr", "username": "RAPMONSTHURR"}, {"id": "874825092135403521", "name": "\ub9ac\uc5bc\ubdd4 REALV \u273f", "username": "REALV1230"}, {"id": "3082338689", "name": "RMPICS\u2077", "username": "RMPICS_twt"}, {"id": "3049546716", "name": "jimin pics", "username": "jiminpics"}, {"id": "3111817826", "name": "jimin pics", "username": "parkjiminpics"}, {"id": "133039721", "name": "\ud83c\udf19", "username": "juslevitae"}, {"id": "3245658931", "name": "GEI\ud83e\udd51", "username": "iinally"}, {"id": "4884275301", "name": "Chiii", "username": "seokjinbaobao"}, {"id": "974946375225036800", "name": "VMINion", "username": "VMINion95"}, {"id": "147237818", "name": "\ub798\ube57\ud83d\udc07\ud83d\udc9c (inactive)", "username": "skyetokki"}, {"id": "3177470738", "name": "DEOKUTOUR", "username": "deokutour"}, {"id": "2356290679", "name": "\u263e alex\u2077", "username": "saddadalex"}, {"id": "1187054144", "name": "BTS \u27ed\u27ec Spain \ud83e\uddc8", "username": "BTS_Spain"}, {"id": "318365584", "name": "Steph", "username": "HallyuBack"}, {"id": "953273548780351489", "name": "chihiro\u2077 {semi ia \ud83d\udcda}", "username": "kookceptional"}, {"id": "889719071134015488", "name": "Aileen \ud83d\udc9c \u2077 \u1d3e\u02b3\u1d52\u1d52\u1da0", "username": "Awake_Aileen"}, {"id": "808735423", "name": "ari\u2765 |still alive|", "username": "mochimislifeu"}, {"id": "2451859873", "name": "Lu \ud83c\udf3f", "username": "ggukieblonde"}, {"id": "964255829573689344", "name": "soulmate\ud83c\udf12\ud83c\udf13\ud83c\udf14", "username": "JClear112"}, {"id": "910680226660626432", "name": "yi nga\u2077\u27ed\u27ec \u02e2\u02b0\u1d49 \u207b \u02b0\u1d49\u02b3 born singer", "username": "EomukandOdeng"}, {"id": "1122445868", "name": "SU CAN FLY", "username": "suga930309com"}, {"id": "121965104", "name": "\ud64d\u6d2aHONG", "username": "MnetKmHONGpd"}, {"id": "130443019", "name": "\ubc15\ucc2c\uc6b1 CHANUK PARK", "username": "rockchan4u"}, {"id": "19141724", "name": "\uc7a5\ub3d9\uc6b0 Chang Dong-woo", "username": "odissy"}, {"id": "2912336186", "name": "\ubc29\ud0c4\uc18c\ub144\ub2e8\uacf5\uc2dd\uc1fc\ud551\ubab0", "username": "BTSOFFICIALSHOP"}, {"id": "1173787748", "name": "BTS A.R.M.Y", "username": "BTS_ARMY"}, {"id": "384458172", "name": "Supreme Boi KOR", "username": "supremeboi94"}, {"id": "741119911993483264", "name": "Vodka\ud83d\udc9c", "username": "Vodka_1230"}, {"id": "720926657532432385", "name": "Just for RM\u2661\u263b", "username": "Justfor_RM"}, {"id": "770629551621672960", "name": "\ub4dc\ub9bc\u68a6\u2661(\u02f6\u203e\u1dc4 \u207b\u032b \u203e\u1dc5\u02f5)\u2661", "username": "dreamon0912"}, {"id": "195979493", "name": "\ubbf8\uc178\uc740 \u2077", "username": "michelle_0816"}, {"id": "952194945045139457", "name": "Tata", "username": "taet95"}, {"id": "968129811427160064", "name": "Ronjue\uff65:*", "username": "Ronjue2"}, {"id": "3291778512", "name": "\ube44\uc8fc\uc5bc\uc1fc\ud06c:VS", "username": "VShock1230"}, {"id": "31339831", "name": "Adam Rippon", "username": "AdamRippon"}, {"id": "971130819518476289", "name": "TIFFANY YOUNG", "username": "tiffanyyoung"}, {"id": "2810118104", "name": "DREAM YUME | JG-REVIEWS:K-POP", "username": "JoeyGeroMusic"}, {"id": "729515927717339136", "name": "Golden Time", "username": "goldentimejjk"}, {"id": "77762149", "name": "Maia Shibutani", "username": "MaiaShibutani"}, {"id": "910926378576486400", "name": "\ubb3c\uacb0", "username": "iiovemywave"}, {"id": "963447975291666432", "name": "DICON_BTS", "username": "Dicon_korea"}, {"id": "887031512578883584", "name": "c\u2077", "username": "koosuns"}, {"id": "952278492078592000", "name": "\u2661", "username": "taehoon_twt"}, {"id": "3392090327", "name": "Suga Dreams", "username": "suga_dreams"}, {"id": "919078065510146049", "name": "\u1d2e\u1d31 \uc9c0\ubbf8\ub2c8\uc9d1 \u2077", "username": "JIMIN_ZIP"}, {"id": "2161614876", "name": "fariha \u2077", "username": "ironchim"}, {"id": "791441644620959744", "name": "2018 Kpop Predictions", "username": "KpopPredixtions"}, {"id": "919539228408659969", "name": "BTS ASIAN LEGENDS \ud83d\udc51", "username": "anpanminsuga"}, {"id": "1957463503", "name": "\ud835\udd07\ud835\udd2f\ud835\udd22\ud835\udd1e\u2077\u263e\u2740", "username": "buteracypher"}, {"id": "366603667", "name": "c\u2077", "username": "joonieskys"}, {"id": "2919019624", "name": "pannchoa", "username": "pannchoa"}, {"id": "235471329", "name": "amber\u2077", "username": "kingtantae"}, {"id": "871149326189305856", "name": "ArMY2013 \u2077 \ud83c\uddfa\ud83c\uddf8", "username": "BTSxHollywood"}, {"id": "862145729472716801", "name": "BTS Updating\u2077", "username": "btsglobally"}, {"id": "35720908", "name": "Brent Battles", "username": "brentbattles"}, {"id": "844026663050473472", "name": "NINETY DEGREES", "username": "ninety_degree5"}, {"id": "812238284030099456", "name": "\u308b\u308b\u308b", "username": "pmgwgmgm1"}, {"id": "741488305288544256", "name": "\uc0e4\uc624\uc9c0\uc5d0\ud83d\udc7c", "username": "yonaxiaojie"}, {"id": "17659206", "name": "Soompi", "username": "soompi"}, {"id": "1692691326", "name": "S.of.Y", "username": "dynaminkoo"}, {"id": "925526198138163201", "name": "wwBTS", "username": "analyticstan"}, {"id": "17019152", "name": "Steve Aoki", "username": "steveaoki"}, {"id": "817198695288569857", "name": "kookadooks\u2077", "username": "tls123_twt"}, {"id": "846779978578505728", "name": "s\u2077", "username": "spreadwings15"}, {"id": "106355755", "name": "TopAchat", "username": "TopAchat"}, {"id": "854123004", "name": "\u2728CAMERON\u2728", "username": "CAM3R0NPH1L1P"}, {"id": "852815111551041536", "name": "lina \u200e\u25e1\u030e", "username": "taekoofiIm"}, {"id": "3710582787", "name": "Jen\u2077 \ud83c\udff3\ufe0f\u200d\ud83c\udf08", "username": "jinminpeach"}, {"id": "846692387485233152", "name": "farah", "username": "luvvpjm"}, {"id": "57107167", "name": "Twibbon", "username": "twibbon"}, {"id": "802690892628774913", "name": "\ud30c\ub8ec", "username": "balloon_wanted"}, {"id": "964489932218818560", "name": "The United Efforts Project", "username": "BTSUnitedEffort"}, {"id": "870895803170041856", "name": "Bamm\u2077", "username": "MuffMuffBTS"}, {"id": "786985030128111616", "name": "\ud83c\udf19\u2601\ufe0f", "username": "myalogue"}, {"id": "38992649", "name": "\uae40\uc601\ub300 Kim Youngdae", "username": "toojazzy25"}, {"id": "3408757743", "name": "ddd2\u2077", "username": "dbnnr"}, {"id": "893047208156602368", "name": "LSST", "username": "laststop_jimin"}, {"id": "2765201402", "name": "\ub7ec\ube0c\uc628\ud0d1\ud83d\udc3b\ud83e\udd19", "username": "BTS_LOVEONTOP"}, {"id": "4921347199", "name": "Means95", "username": "Means951013"}, {"id": "722331536624717824", "name": "\uc2a4\ud0c0\ub77c\uc774\ud2b8\ud83c\udf1f\uce68", "username": "starlight_chim"}, {"id": "1563985212", "name": "\ud83d\udc4d\uc544\uc774\ub77c\uc774\ud0b7", "username": "ILIKEIT_JM"}, {"id": "712088540830572544", "name": "\ubbf8\ub2c8\ub9c8\uc6b0\uc2a4\u263a(MINI MOUTH)", "username": "JIMINIMOUTH"}, {"id": "705050815086505984", "name": "\ub9ac\ud2c0\ube14\ub77c\uc378\ud83d\udc25", "username": "Lblossom1013"}, {"id": "786696140104269825", "name": "prussianblue\ud83d\udc3e", "username": "951013_jimin"}, {"id": "3366124972", "name": "\ub9c8\uc774\ud2f0\uc81c\uc774", "username": "mighty_jimin"}, {"id": "870999707165769728", "name": "\ub7ec\ube0c\uc2e0\uc2a41997", "username": "Lovesince1997"}, {"id": "4623634932", "name": "\ub2e8\ub378\ub9ac\uc628", "username": "dandelionforjin"}, {"id": "903686215005741056", "name": "Steamed Vread\u270c\ud83c\udffb\ufe0f", "username": "SV_951230"}, {"id": "913657305241075713", "name": "Love, Affection", "username": "loveaffection_V"}, {"id": "939900103757676544", "name": "\ud551\ud06c \ubdd4\u2764\ufe0ePINK V", "username": "PINK_V1230"}, {"id": "903993970010632194", "name": "\ud30c\uc2a4\ud154\ubb34\ub4dc PASTELMOOD", "username": "PastelMoodJin"}, {"id": "953663868659798017", "name": "Soo Choi \ud83d\udc9c 0610 (REST)", "username": "choi_bts2"}, {"id": "840494833844252672", "name": "piecesofmind", "username": "piecesofmind_jm"}, {"id": "902485138889510912", "name": "Lupinus Hope \ud83c\udf40 \ub8e8\ud53c\ub108\uc2a4\ud649 \ud83d\udc3f", "username": "Lupine218"}, {"id": "2587916678", "name": "STICK WITH YOU", "username": "StickwitU_jk"}, {"id": "790200916381052928", "name": "\ub2e4\uc774\uc544\ubaac\ub4dc \ub354\uc2a4\ud2b8", "username": "Diamond_97jk"}, {"id": "825328697209020419", "name": "\ud83c\udf0cHope Utopia\ud83c\udf0c SLOW", "username": "Hope_utopia"}, {"id": "3016312933", "name": "\uc544 \uc774 \uc288 \uac00", "username": "isuga93"}, {"id": "717351348807671809", "name": "j-hope Bar", "username": "J_hopeBarChina"}, {"id": "2934697057", "name": "BTS SG\ud83c\uddf8\ud83c\uddec", "username": "Bulletproof_SG"}, {"id": "844847218783797249", "name": "\uc800\uc2a4\ud2b8\ube44\ud649\ud83c\udf40\u3010slow\u3011", "username": "justbehope218"}, {"id": "2392691502", "name": "HopeSmiling\ud83d\ude0a", "username": "HopeSmiling0218"}, {"id": "2847202303", "name": "\ub354\ud638\uc4f0,, \ud83e\uddf8\ud83c\udf6d", "username": "THEHO218"}, {"id": "804166556569608196", "name": "\ub2ec \uc18c\ub144, The moonboy", "username": "moonboy_jk"}, {"id": "766276684391776256", "name": "CHINA Baidu Vbar", "username": "KIMTAEHYUNGBAR_"}, {"id": "901499057864048640", "name": "DTownsonic", "username": "dtownsonic_suga"}, {"id": "902754181458644992", "name": "SniperJK", "username": "Sniper_JK0901"}, {"id": "855034446310854656", "name": "HARU \ud83d\udc33", "username": "haru130613_"}, {"id": "914423875802296322", "name": "jinKissLetsgo", "username": "jinKissLetsgo"}, {"id": "788391927557218308", "name": "zack", "username": "NFTscj"}, {"id": "852887701346893825", "name": "\ub7fd\uc778\ud0dc\ud0dc\ud83e\uddf8", "username": "Luvin_taetae"}, {"id": "2320481004", "name": "mischievous-sugar \ubbf8\uc2a4\uce58\ubc84\uc2a4\uc288\uac00", "username": "mischievous0309"}, {"id": "811830509609230336", "name": "Vberryya", "username": "vberryya1230"}, {"id": "2257614936", "name": "IT'S YOUR DAY!", "username": "itsyourday0613"}, {"id": "2889482016", "name": "fistbump", "username": "fistbump_suga"}, {"id": "3186502825", "name": "\uc288\uac00\uc628\ub354\ube44\ud2b8", "username": "sugaonthebeat39"}, {"id": "768746989307568128", "name": "309%", "username": "309percent_suga"}, {"id": "743107953658466304", "name": "\uc288\uac00\uc5b4\ud0dd \ud83d\udc98", "username": "suga_attack0309"}, {"id": "747060351863300096", "name": "alloveryou", "username": "alloveryou0309"}, {"id": "4388646680", "name": "\uc724\uae30\uc758 \ubaa9\uce94\ub514  l  MOKCANDY", "username": "forsuga_0309"}, {"id": "732105632669523969", "name": "MORE THAN TOMORROW", "username": "morethan0309"}, {"id": "799639835161960448", "name": "\ube14\ub799\ud0dc\ud0dc", "username": "blacktaetae1230"}, {"id": "791294657661591552", "name": "MAJOR SCALE", "username": "majorscale_kr"}, {"id": "4902802057", "name": "SUMMER MAGIC", "username": "summer_magicV"}, {"id": "744803465734459394", "name": "LoveandTrue_VSUGA", "username": "loveandtrue_"}, {"id": "2931834606", "name": "\ud3ec\uc5d0\ubc84\ud3ec\ubdd4\ud83c\udf38", "username": "ffv951230"}, {"id": "2927064158", "name": "\ud15c\ud37c\ub7ec\ucc9812.30\u00b0V", "username": "temperature_v"}, {"id": "701431887915405316", "name": "ASTT:\uc5b4\uc378\ud0dc\ud0dc\u2077\ud83d\udc9c", "username": "ASOMETAETAE1230"}, {"id": "4677751411", "name": "VIVID BLACK", "username": "vividblack1230"}, {"id": "2993692928", "name": "DelightV\ud83c\udf52", "username": "1995_1230com"}, {"id": "4740525163", "name": "CARAMEL\u00d7VS:\uce74\ub77c\uba5c\ubdd4\uc5d0\uc2a4", "username": "caramelvs9395"}, {"id": "734383070954954752", "name": "\ud83d\udc33Sweet Ocean\ud83d\udc33", "username": "sweetocean1230"}, {"id": "1880099558", "name": "\uc601\ud654\ub294 \ubc29\uc6b8\ubc29\uc6b8", "username": "MovieBangwool"}, {"id": "1508682266", "name": "HARUHARU\u2728", "username": "haru951230"}, {"id": "2515894147", "name": "\ud22c\ub9c8\uc774\ub2ec\ub9c1 TOMYDARLINGV", "username": "TO_MY_DARLINGV"}, {"id": "3282821185", "name": "BONNIE BUTTERFLY\u2728", "username": "Bonnie_9595"}, {"id": "3856838593", "name": "\ud06c\ub808\uc13c\ub3c4\ud83d\udc9c", "username": "crescendo_1230"}, {"id": "789235298257350656", "name": "OnlyForTAETAE", "username": "OnlyForTAETAE_"}, {"id": "830157861942607874", "name": "\uc870\ud61c\uc6d0\ud83d\udc9c", "username": "BTS_ARMY_INT"}, {"id": "920019286676172800", "name": "BTS Charts", "username": "btschartdata"}, {"id": "1890746246", "name": "\uc624\ub298\uc758 \ubc15\uc9c0\ubbfc", "username": "TODAY_PJM"}, {"id": "2271865489", "name": "\uafc0\ubb3c:HNWT", "username": "honeywater_jm"}, {"id": "2402418018", "name": "MNMT", "username": "miningfulmoment"}, {"id": "1582411400", "name": "\uc7bc\uc7bc JAMJAM", "username": "parkjamjam_kr"}, {"id": "2280834240", "name": "\ud3ec\uce08 FORTUNE", "username": "1997_0901com"}, {"id": "2472336674", "name": "Little Golden", "username": "LittleGolden97"}, {"id": "2754726918", "name": "\ud37c\uba38\ub10c\ud2b8 \ub808\ub4dc", "username": "PERMANENT__RED"}, {"id": "3813954498", "name": "PURE VOW", "username": "purevow_JK"}, {"id": "794851569086787584", "name": "\uad6d\uac00\ub300\ud45c", "username": "kookdae97"}, {"id": "739617812642074624", "name": "MELLIFLUOUS J\ud83c\udf38", "username": "mellifluousJK"}, {"id": "782830015058554881", "name": "MORE THAN EVER", "username": "morethanever_jk"}, {"id": "2920392169", "name": "BEYOND it.", "username": "BEYONDIT_0901"}, {"id": "733787864232820736", "name": "SERENITY JK", "username": "serenity_jk"}, {"id": "919042236465086467", "name": "\ud83c\udf68", "username": "jk_milk_it"}, {"id": "553095500", "name": "GOLDEN PEACH \ud83d\udc9b", "username": "jeonglows"}, {"id": "793995591571374080", "name": "Daily Yoonjin", "username": "dailyyoonjin"}, {"id": "4198697832", "name": "\uac10\uc790\ucc98\ub140", "username": "AUNT_POTATO_"}, {"id": "2300824406", "name": "\uc774\ub354\ub9ac\uc5bc", "username": "ethereal_jimin"}, {"id": "846112272078524416", "name": "BTS FRANCE\u2077 \ud83d\udc0b\ud83e\uddc8", "username": "BTSFRANCE_"}, {"id": "230761964", "name": "korea dispatch", "username": "dispatchsns"}, {"id": "872285845880832000", "name": "jenny\ud83c\udf8b\u2077", "username": "taerouge"}, {"id": "873893019120013314", "name": "BTS Request\u2077", "username": "BTSRequest"}, {"id": "609058371", "name": "myra\u2077", "username": "jimincIoud"}, {"id": "2467992500", "name": "US BTS ARMY \u2077", "username": "USBTSARMY"}, {"id": "791865335120928768", "name": "\ud83d\udc9c\ud83d\udd0dBTS ARMY League\u2077\ud83d\udd0e\ud83d\udc9c", "username": "BTS_ARMYLeague"}, {"id": "858293106332094464", "name": "\u2661", "username": "026vmn"}, {"id": "806179924407107585", "name": "BTS on Billboard \u2077 (REST)", "username": "BTS_Billboard"}, {"id": "773218019677835264", "name": "BTS \ub3c5\ub824\uc5f0\ud569", "username": "BTS_KR_ARMY"}, {"id": "960719628837076992", "name": "\ubc29\ud0c4\uc18c\ub144\ub2e8 \uc74c\uc6d0\uc815\ubcf4\ud300 (52Hz)", "username": "ARMY52Hz"}, {"id": "2406145385", "name": "\u2764 Mother Nature \u2764", "username": "sheiluchi24"}, {"id": "555103278", "name": "peachisoda\ud83d\ude0e", "username": "peachisoda"}, {"id": "767034591261564928", "name": "JUST DO EAT \ud83c\udf19", "username": "justdoeat_jin"}, {"id": "4671824905", "name": "FREE LOOP", "username": "freeloop_jin"}, {"id": "740607887274168320", "name": "\uc801\ub3c4\ud83d\udd25", "username": "thequator1204"}, {"id": "3285486260", "name": "Apple Tape \u26a1 \uc560\ud50c\ud14c\uc78e", "username": "appletapebts"}, {"id": "334927674", "name": "\ud83c\udf27\ufe0f\u2077", "username": "laughkpop"}, {"id": "3647356272", "name": "\ubaa8\ub2c8\uc8fc\ub2c8", "username": "MoNiJunNi"}, {"id": "818392096667090944", "name": "\ud37c\ud50c \ubdd4 \ud83d\udc2f\ud83d\udc9c(close)", "username": "PURPLETIGERV"}, {"id": "845703045354696704", "name": "\uff4d\uff41\uff43\uff32\uff4f\uff43\uff4f\uff53\uff2d [ REST ]", "username": "macRocosM912"}, {"id": "134661364", "name": "\ud478\ub9c8\ucf54\ub9ac\uc544 PUMA Korea", "username": "pumakorea"}, {"id": "948660693984784384", "name": "BTS Fambases \ud83d\udc9c\u2077", "username": "BTS_Fambases"}, {"id": "2923737857", "name": "diane\u2077", "username": "vantejkvm"}, {"id": "772793518540455941", "name": "Jungkookpie", "username": "jeonss97"}, {"id": "876733791447818240", "name": "\u25e1\u0308", "username": "taebokkiii"}, {"id": "154497854", "name": "everything is ok\ud83e\udde1", "username": "OK_JUNGKOOK_NET"}, {"id": "781687001523171328", "name": "TENSION UP", "username": "tensionup_1013"}, {"id": "2933735300", "name": "VTAC", "username": "V_TAC1230"}, {"id": "4781791644", "name": "\u064e", "username": "hopingyoonmin"}, {"id": "3228191803", "name": "Winter StrawVerry\u2744\ud83c\udf53", "username": "winterVerry1230"}, {"id": "833285875563851778", "name": "\uafc0 \ud788\ud788", "username": "HONEY_o8o"}, {"id": "928629119780302848", "name": "BTS FANCAFE", "username": "btsfancafe__twt"}, {"id": "3479742436", "name": "\u265b\ud83c\udf84", "username": "sceneryfortae"}, {"id": "800347530026315776", "name": "\u1d2e\u1d31kate\u2077 2022.06.10 NEW ALBUM!!", "username": "bangtanvitamia"}, {"id": "918830896462958592", "name": "paui \u2763\ufe0f", "username": "skzchoo"}, {"id": "815676584204128256", "name": "ARMY NATION\u2122", "username": "armynation_tm"}, {"id": "859452726031376386", "name": "BTS Europe ARMY\u2077 | 10.06.22 (rest)", "username": "BTSEuropeARMY"}, {"id": "728927220131975168", "name": "sam\u2b50\ufe0f", "username": "perfectlyjimin"}, {"id": "920635759320735745", "name": "\ud06c\ub9bd\ud1a0 \ud328\ubc00\ub9ac (Crypto family)", "username": "RHnKHhhb"}, {"id": "1560555878", "name": "Diana\u2077 \ud83c\udde6\ud83c\uddf7 \ud83c\uddf0\ud83c\uddf7 2022.06.10", "username": "MayaPark28"}, {"id": "864525927438536707", "name": "worldwideBTS", "username": "btsanalytics"}, {"id": "739991011544338432", "name": "Peach Jelly", "username": "peach_jelly1013"}, {"id": "904997336274747392", "name": "Eloise \ud83c\udf0c", "username": "TaeTaeStellar"}, {"id": "894564021315092481", "name": "\u1d2e\u1d31For BTS & ARMY", "username": "for_ARMYs"}, {"id": "827443926156013568", "name": "Jim-in | WITH YOU JIMIN \ud83d\udc99", "username": "__jim_in"}, {"id": "888669552657088512", "name": "\ud585\ud558\ub9ac", "username": "haphariii"}, {"id": "1591131403", "name": "BTS National\u2077", "username": "BTS_National"}, {"id": "2575219062", "name": "Jimin BTS - France | #WeAreFUE", "username": "Jimin_France"}, {"id": "1307746896", "name": "BANGTAN FRANCE", "username": "BTS_France"}, {"id": "952386588255940608", "name": "BTS Army PR", "username": "TheBTSDreamTeam"}, {"id": "743432841371885568", "name": "[rest] peachBOY", "username": "peachBOY_0613"}, {"id": "878100143534243841", "name": "SuperStar BTS", "username": "SuperStarBTStwt"}, {"id": "930008859401318400", "name": "BBB \uff1e\u1d17\uff1c", "username": "BITBYBIT_JK"}, {"id": "2366214054", "name": "\ud0dc\ud0dc\ub79c\ub4dc", "username": "TAETAELAND"}, {"id": "4593179485", "name": "TOPFLIGHT", "username": "topflight_jk"}, {"id": "747451476906123264", "name": "BBEWITHU", "username": "bbewithu"}, {"id": "4872565398", "name": "Jack", "username": "zacktwt"}, {"id": "2932934466", "name": "with luv,", "username": "jeongmilk"}, {"id": "874757267320578049", "name": "Ath\u0113naa", "username": "Athenaa_MD"}, {"id": "234212881", "name": "(slow)\uc544\ubbf8\uc0b4\ub871 \u1d00\u0280\u1d0d\u028f s\u1d00\u029f\u1d0f\u0274", "username": "BTSARMY_Salon"}, {"id": "438447883", "name": "safi", "username": "absolutejeon"}, {"id": "771515461196447744", "name": "cess\u2077", "username": "veIvetkth"}, {"id": "1510583168", "name": "\ub098\uc544\uac08\uc9c4", "username": "improving_Jin"}, {"id": "4817381198", "name": "ByMySide\u221eKookV", "username": "ByMySide_KookV"}, {"id": "729613061363884032", "name": "\u1d0a\u1d07\u029f\u029f\u028f\u0299\u1d07\u1d00\u0274s", "username": "JELLYBEANS_HJ"}, {"id": "833209706113937411", "name": "Taeholic: \ud0dc\ud640\ub9ad", "username": "Taeholic_V"}, {"id": "906915711083094016", "name": "\ud5c8\ub2c8\uc8fc\ub2c8", "username": "HoneyJoonie94"}, {"id": "2838824780", "name": "12\uc6d4\uc758 \ucc30\ub098*\u2732\uff9f*\uff61 \u266a", "username": "December_JIN_"}, {"id": "864501256437485568", "name": "\ud638\ud504\uc544\uc774\uc2a4\ud83d\udc40", "username": "HOPEYES218"}, {"id": "742035378077499394", "name": "OFF THE DEEP END", "username": "BTS_JIMINI95"}, {"id": "2183987364", "name": "SNOWPEACH\u2744", "username": "JUNGKOOKcokr"}, {"id": "717280230809800704", "name": "\uc9c4\uc800", "username": "ginger4him"}, {"id": "3282185924", "name": "MADE IN 1997", "username": "madein1997_jk"}, {"id": "926680717286715392", "name": "haruharu\ud83d\udc9c (slow)", "username": "haruharu_w_bts"}, {"id": "755541622977400832", "name": "BLACKPINK_4EVER", "username": "BLACK_PINK4ever"}, {"id": "2271458031", "name": "\ud83d\udc9c Hoseok's Sunray  \ud83d\udc9c", "username": "GKBJ0218"}, {"id": "931470546134429697", "name": "blackpink\u2019s style", "username": "blackpinksstyle"}, {"id": "3041409234", "name": "\uc625\uc0c1\uc758 \ubbfc\ub4e4\ub808\uaf43\ud83c\udf3c", "username": "origamifirefly"}, {"id": "804866931857584128", "name": "URUHIKO", "username": "uruhiko_kpop"}, {"id": "21621886", "name": "Jeff Benjamin", "username": "Jeff__Benjamin"}, {"id": "1569301536", "name": "SPOTLIGHT BTS\u2077", "username": "SPOTLIGHTBTS"}, {"id": "3291523489", "name": "BECAUSE OF V", "username": "becauseofV95"}, {"id": "790050185120362497", "name": "\ub204\ub098\ube44(NUNA V)", "username": "_nuna_V"}, {"id": "743781775005016064", "name": "MOV", "username": "951230_MOV"}, {"id": "1402988305", "name": "BTS Translations / Bangtansubs", "username": "BTS_Trans"}, {"id": "809550621279821824", "name": "Mass Voting Project", "username": "BTSxMVP"}, {"id": "708259525292232704", "name": "lily \u2077", "username": "babyggloss"}, {"id": "1516498494", "name": "BTSBPHKFC", "username": "BTSHK_BTSBPHKFC"}, {"id": "2877627180", "name": "BTS INTERNATIONAL", "username": "BTSARMY_INTL"}, {"id": "894537112225067008", "name": "BT21", "username": "BT21_"}, {"id": "153657620", "name": "\uc1a1\ud638\ubc94", "username": "01020120606"}, {"id": "607072006", "name": "\uc190\uc131\ub4dd", "username": "sonsungdeuk"}, {"id": "178548929", "name": "Lumpens", "username": "lumpenss"}, {"id": "920160588650516480", "name": "LOVE MYSELF", "username": "bts_love_myself"}, {"id": "3036268803", "name": "Tancr\u00e8de \u0646", "username": "Tancrede_Crptrs"}, {"id": "751003684167905280", "name": "Jennie Kim Updates", "username": "JennieKUpdates"}, {"id": "4656625635", "name": "MalaiseTV", "username": "malaisetele"}, {"id": "796579760893784065", "name": "KARD", "username": "KARD_Official"}, {"id": "864816088353193984", "name": "Paint It Black", "username": "PaintItBlack_JN"}, {"id": "4620073545", "name": "BTS fashion", "username": "in_BTScloset"}, {"id": "823132494098731008", "name": "BTS Channel+", "username": "bangtanpIus"}, {"id": "799866413376684033", "name": "Dear My Queen", "username": "kimjennie116"}, {"id": "763386100056403968", "name": "Florence\ud83c\udf38", "username": "florence_JN"}, {"id": "762905330862792705", "name": "Black J", "username": "960116_J"}, {"id": "2272654854", "name": "BLACKPINK \ud83d\udcad COMEBACK \ube14\ub799\ud551\ud06c - HOW YOU LIKE THAT", "username": "YG_BLACKPINK"}, {"id": "2613511795", "name": "BL\u039bCKPI\u0418K GLOBAL", "username": "BLACKPINKGLOBAL"}, {"id": "773131287179567104", "name": "\ub9ac\uc0ac\ub2f7\ucef4 (LISA)", "username": "BP970327"}, {"id": "2609580764", "name": "\ud83d\udda4\uae40\uc81c\ub2c8\ub2f7\ucef4\ud83d\udc97", "username": "960116_dot"}, {"id": "760500035154948096", "name": "Kiss and Hug", "username": "xoxo_jennierose"}, {"id": "963647047", "name": "Makenna", "username": "makenna_mg"}, {"id": "864113100873543681", "name": "VintageWine", "username": "VintageWine1230"}, {"id": "1878450026", "name": "BTS JAPAN OFFICIAL", "username": "BTS_jp_official"}, {"id": "4768552152", "name": "\ud30c\uc774\uc2dc\uc988", "username": "piscesboy_suga"}, {"id": "167025026", "name": "Pdogg", "username": "pddogg"}, {"id": "1583812734", "name": "SlowRabbit", "username": "SlowRabbit_no1"}, {"id": "165033159", "name": "hitman", "username": "hitmanb"}, {"id": "278662460", "name": "Billboard Music Awards", "username": "BBMAs"}, {"id": "206500951", "name": "\ubc15\ubcf4\uac80", "username": "BOGUMMY"}, {"id": "742988562652663809", "name": "BLACKPINK BLINK UNION\ud83c\udf37", "username": "BBU_BLACKPINK"}, {"id": "739725829496705025", "name": "blackpink closet", "username": "blackpinkcloset"}, {"id": "603439428", "name": "p", "username": "lifelinetae"}, {"id": "180369797", "name": "TOGEN", "username": "togen"}, {"id": "3131557841", "name": "Beyond The Style \u273c Alex \u273c", "username": "GetOnSwag"}, {"id": "886978460", "name": "Linkis.com", "username": "Linkis_com"}, {"id": "733313277552254978", "name": "BLACKPINK STYLE", "username": "blackpinkoutfit"}, {"id": "1468067424", "name": "UNILAD Grub", "username": "UNILAD_Grub"}, {"id": "281766200", "name": "Dylan O'Brien", "username": "dylanobrien"}, {"id": "21366823", "name": "allkpop", "username": "allkpop"}, {"id": "632110916", "name": "Amber Liu \u5218\u9038\u4e91", "username": "amberliu"}, {"id": "168683422", "name": "BIGHIT MUSIC", "username": "BIGHIT_MUSIC"}, {"id": "489748500", "name": "\uae40\uc885\ud604", "username": "realjonghyun90"}, {"id": "1409798257", "name": "BTS_official", "username": "bts_bighit"}, {"id": "420164165", "name": "\u1d22\u1d07\u029f\u1d0f", "username": "ZELO96"}, {"id": "361062981", "name": "Himchan", "username": "CHANISMOfficial"}, {"id": "335141638", "name": "\ubc29\ud0c4\uc18c\ub144\ub2e8", "username": "BTS_twt"}, {"id": "466127190", "name": "Jongup_Official", "username": "jongup_official"}, {"id": "465219474", "name": "BAP_Youngjae", "username": "BAP_Youngjae"}, {"id": "23375688", "name": "Selena Gomez", "username": "selenagomez"}, {"id": "2296563338", "name": "BTS DIARY", "username": "btsdiary"}, {"id": "723884990", "name": "\uae40\uc131\uaddc", "username": "kyuzizi"}, {"id": "43509988", "name": "tablo", "username": "blobyblo"}, {"id": "224214495", "name": "G-Dragon World \uad8c\uc9c0\uc6a9", "username": "GDragonIndo"}, {"id": "6661522", "name": "cyprien", "username": "MonsieurDream"}, {"id": "218100123", "name": "KGP-KGN", "username": "kgp700"}, {"id": "390860562", "name": "Stumbler Videos", "username": "StumblerVideos"}, {"id": "17674486", "name": "\ud835\udcdc", "username": "MichellePhan"}, {"id": "2873899906", "name": "Nelliou44", "username": "nelliou_moix44"}, {"id": "230527949", "name": "Anonymous Press", "username": "AnonymousPress"}, {"id": "69580103", "name": "Anonymous Germany", "username": "AnonymousGer"}, {"id": "279390084", "name": "Anonymous", "username": "YourAnonNews"}, {"id": "27260086", "name": "Justin Bieber", "username": "justinbieber"}, {"id": "25753258", "name": "MikaWebsite[.Com!]", "username": "MikaWebsite"}, {"id": "40080940", "name": "Vera Wang", "username": "VeraWang"}, {"id": "326359913", "name": "CHANEL", "username": "CHANEL"}, {"id": "24296476", "name": "MIKA", "username": "mikasounds"}, {"id": "348379865", "name": "Dior", "username": "Dior"}]